{
  "time_periods": 12,
  "demand": [
    26089.9326691,
    24964.3953213,
    24325.3179734,
    24163.1706255,
    24719.2732776,
    25997.3159298,
    27963.1685819,
    29824.691234,
    31948.2538862,
    34162.5465383,
    36242.5691904,
    38159.9918426
  ],
  "reserves": [
    260.899326691,
    249.643953213,
    243.253179734,
    241.63170625499998,
    247.192732776,
    259.973159298,
    279.63168581900004,
    298.24691234000005,
    319.482538862,
    341.625465383,
    362.42569190399996,
    381.599918426
  ],
  "thermal_generators": {
    "GEN7774": {
      "must_run": 1,
      "power_output_minimum": 0.13,
      "power_output_maximum": 3.65,
      "ramp_up_limit": 25,
      "ramp_down_limit": 25,
      "ramp_startup_limit": 25.13,
      "ramp_shutdown_limit": 25.13,
      "time_up_minimum": 1,
      "time_down_minimum": 1,
      "power_output_t0": 0.13,
      "unit_on_t0": 1,
      "time_up_t0": 1,
      "time_down_t0": 0,
      "startup": [
        {
          "lag": 1,
          "cost": 0.0325
        },
        {
          "lag": 2,
          "cost": 0.04875
        }
      ],
      "piecewise_production": [
        {
          "mw": 0.13,
          "cost": 0.0049585
        },
        {
          "mw": 0.65,
          "cost": 0.0181925
        }
      ],
      "name": "GEN7774"
    },
    "GEN8085": {
      "must_run": 1,
      "power_output_minimum": 0.376,
      "power_output_maximum": 1.88,
      "ramp_up_limit": 25,
      "ramp_down_limit": 25,
      "ramp_startup_limit": 25.376,
      "ramp_shutdown_limit": 25.376,
      "time_up_minimum": 1,
      "time_down_minimum": 1,
      "power_output_t0": 0.376,
      "unit_on_t0": 1,
      "time_up_t0": 1,
      "time_down_t0": 0,
      "startup": [
        {
          "lag": 1,
          "cost": 0.094
        },
        {
          "lag": 2,
          "cost": 0.141
        }
      ],
      "piecewise_production": [
        {
          "mw": 0.376,
          "cost": 0.0143492
        },
        {
          "mw": 1.88,
          "cost": 0.052626
        }
      ],
      "name": "GEN8085"
    },
    "GEN5901": {
      "must_run": 1,
      "power_output_minimum": 0.09,
      "power_output_maximum": 0.3,
      "ramp_up_limit": 25,
      "ramp_down_limit": 25,
      "ramp_startup_limit": 25.09,
      "ramp_shutdown_limit": 25.09,
      "time_up_minimum": 1,
      "time_down_minimum": 1,
      "power_output_t0": 0.09,
      "unit_on_t0": 1,
      "time_up_t0": 1,
      "time_down_t0": 0,
      "startup": [
        {
          "lag": 1,
          "cost": 0.015
        },
        {
          "lag": 2,
          "cost": 0.0225
        }
      ],
      "piecewise_production": [
        {
          "mw": 0.09,
          "cost": 0.0029448
        },
        {
          "mw": 0.3,
          "cost": 0.009816
        }
      ],
      "name": "GEN5901"
    }
  },
  "renewable_generators": {
    "215_HYDRO_3": {
      "power_output_minimum": [
        9.3,
        9.3,
        9.1,
        9.9,
        18.5,
        18.5,
        18.7,
        18.7,
        18.5,
        8.2,
        10.7,
        9.3,
        9.3,
        9.5,
        17.1,
        18.7,
        18.5,
        18.7,
        18.5,
        9.9,
        9.3,
        9.5,
        9.3,
        9.3,
        9.5,
        9.3,
        9.5,
        9.3,
        17.9,
        17.9,
        18.1,
        17.9,
        18.1,
        12.1,
        9.3,
        9.3,
        9.3,
        9.1,
        16.9,
        18.5,
        18.9,
        18.5,
        18.5,
        12.6,
        9.3,
        9.5,
        9.3,
        9.5
      ],
      "power_output_maximum": [
        9.3,
        9.3,
        9.1,
        9.9,
        18.5,
        18.5,
        18.7,
        18.7,
        18.5,
        8.2,
        10.7,
        9.3,
        9.3,
        9.5,
        17.1,
        18.7,
        18.5,
        18.7,
        18.5,
        9.9,
        9.3,
        9.5,
        9.3,
        9.3,
        9.5,
        9.3,
        9.5,
        9.3,
        17.9,
        17.9,
        18.1,
        17.9,
        18.1,
        12.1,
        9.3,
        9.3,
        9.3,
        9.1,
        16.9,
        18.5,
        18.9,
        18.5,
        18.5,
        12.6,
        9.3,
        9.5,
        9.3,
        9.5
      ],
      "name": "215_HYDRO_3"
    },
    "320_PV_1": {
      "power_output_minimum": [
        0,
        0,
        0,
        0,
        0,
        0,
        0,
        0,
        0,
        0,
        0,
        0,
        0,
        0,
        0,
        0,
        0,
        0,
        0,
        0,
        0,
        0,
        0,
        0,
        0,
        0,
        0,
        0,
        0,
        0,
        0,
        0,
        0,
        0,
        0,
        0,
        0,
        0,
        0,
        0,
        0,
        0,
        0,
        0,
        0,
        0,
        0,
        0
      ],
      "power_output_maximum": [
        0,
        0,
        0,
        0,
        0,
        0,
        0,
        26.7,
        34.5,
        35.2,
        34.3,
        34.1,
        35.1,
        33.6,
        30.2,
        18.7,
        0,
        0,
        0,
        0,
        0,
        0,
        0,
        0,
        0,
        0,
        0,
        0,
        0,
        0,
        0,
        26,
        33.5,
        34.1,
        34,
        33.5,
        33.6,
        31.7,
        27.7,
        18.3,
        0,
        0,
        0,
        0,
        0,
        0,
        0,
        0
      ],
      "name": "320_PV_1"
    },
    "308_RTPV_1": {
      "power_output_minimum": [
        0,
        0,
        0,
        0,
        0,
        0,
        0,
        15.5,
        37.6,
        53.2,
        64.5,
        68.2,
        68.5,
        61.8,
        45.4,
        21.2,
        0,
        0,
        0,
        0,
        0,
        0,
        0,
        0,
        0,
        0,
        0,
        0,
        0,
        0,
        0,
        15.8,
        38.5,
        53.8,
        65,
        71.8,
        68.8,
        59.7,
        44.4,
        19,
        0,
        0,
        0,
        0,
        0,
        0,
        0,
        0
      ],
      "power_output_maximum": [
        0,
        0,
        0,
        0,
        0,
        0,
        0,
        15.5,
        37.6,
        53.2,
        64.5,
        68.2,
        68.5,
        61.8,
        45.4,
        21.2,
        0,
        0,
        0,
        0,
        0,
        0,
        0,
        0,
        0,
        0,
        0,
        0,
        0,
        0,
        0,
        15.8,
        38.5,
        53.8,
        65,
        71.8,
        68.8,
        59.7,
        44.4,
        19,
        0,
        0,
        0,
        0,
        0,
        0,
        0,
        0
      ],
      "name": "308_RTPV_1"
    }
  }
}